openie/__init__.py
openie/openie.py
stanford_openie-1.3.2.dist-info/LICENSE
stanford_openie-1.3.2.dist-info/METADATA
stanford_openie-1.3.2.dist-info/WHEEL
stanford_openie-1.3.2.dist-info/top_level.txt
stanford_openie-1.3.2.dist-info/RECORD
