Metadata-Version: 2.1
Name: stanford-openie
Version: 1.3.2
Summary: Minimalist wrapper around Stanford OpenIE
Author: Philippe Remy
License: MIT
License-File: LICENSE
Requires-Dist: wget
Requires-Dist: stanfordnlp
Requires-Dist: six
Requires-Dist: pydot
Requires-Dist: protobuf (<=3.20)
